crystflow/__init__.py
crystflow/helpers/__init__.py
crystflow/helpers/list_generator.py
crystflow/helpers/merge_streams.py
crystflow/helpers/scheduler.py
crystflow/helpers/subsample_list.py
crystflow/indexing/__init__.py
crystflow/indexing/detector_refinement.py
crystflow/indexing/grid_search.py
crystflow/indexing/grid_stats.py
crystflow/indexing/indexamajig.py
crystflow/partialator/post_processing.py
crystflow-0.0.1.dist-info/licenses/LICENSE
crystflow-0.0.1.dist-info/METADATA
crystflow-0.0.1.dist-info/WHEEL
crystflow-0.0.1.dist-info/top_level.txt
crystflow-0.0.1.dist-info/RECORD
