Metadata-Version: 2.4
Name: crystflow
Version: 0.0.1
Summary: Name reservation for WIP package
Author-email: Ryan ODea <ryan.odea@psi.ch>
Maintainer-email: Ryan ODea <ryan.odea@psi.ch>
License-Expression: MIT
Keywords: crystallography,data processing
License-File: LICENSE
Dynamic: license-file
